Workbook

Sheet 📊 Сводка
A1: ИНВЕСТИЦИОННЫЙ ПЛАН — 10 000 000 сум / месяц
A3: ⚙️ ВВОДНЫЕ ДАННЫЕ (синие ячейки — изменяемые параметры)
A5: Ежемесячный взнос | B5: 10000000 | C5: Сумма ежемесячных вложений
A6: Остаток кредита | B6: 170000000
A7: Ставка кредита (годовых) | B7: 0.33
A8: Номинальная купонная ставка ИИС | B8: 0.26
A9: Наценка к номиналу ИИС | B9: 0.06
A10: Эффективная ставка ИИС (после наценки) | B10: 0.24
A11: Ставка НДФЛ (возврат) | B11: 0.12
A12: Номинальная ставка вклада | B12: 0.21
A13: Эффективная ставка вклада (с капит.) | B13: 0.23
A14: Количество месяцев (план) | B14: 12
A16: 📈 СРАВНЕНИЕ ТРЁХ СЦЕНАРИЕВ — 12 МЕСЯЦЕВ
A17: Сценарий | B17: Вложено (сум) | C17: Доход / Экономия (сум) | D17: Доход % | E17: Эффект. ставка | F17: Остаток кредита на конец года | G17: Ликвидность | H17: Рейтинг
A18: 🏦 ИИС Облигации + НДФЛ | B18: =B14*B5 -> 120000000 | C18: =B5*B10/12*(B14*(B14+1)/2)+B11*B14*B5 -> 30000000 | D18: =C18/B18 -> 0.25 | E18: =B10+B11 -> 0.36 | F18: 170 000 000 (не меняется) | G18: Средняя | H18: ⭐⭐⭐ #1 — Лучший вариант
A19: 💳 Кредит (доп. платёж к погашению) | B19: =B14*B5 -> 120000000 | C19: =B7/12*B5*B14*(B14-1)/2 -> 18150000 | D19: =C19/B19 -> 0.15125 | E19: =B7 -> 0.33 | F19: ~50 000 000 (-120 млн долга!) | G19: Низкая | H19: ⭐⭐ #2 — Надёжный выбор
A20: 🏧 Вклад 23% (с капитализацией) | B20: =B14*B5 -> 120000000 | C20: =B5*((1+B12/12)^B14-1)/(B12/12)-B14*B5 -> 12251037 | D20: =C20/B20 -> 0.10209198 | E20: =B13 -> 0.23 | F20: 170 000 000 (не меняется) | G20: Высокая | H20: ⭐ #3 — Консервативно
A22: 💡 ВЫВОД: ИИС даёт ~36% эффективных (купон 24% + возврат НДФЛ 12%) — это ВЫГОДНЕЕ кредита (33%). Оптимально: весь излишек → ИИС Облигации.
A24: 📅 РЕЗУЛЬТАТ ЗА ОСТАВШИЕСЯ МЕСЯЦЫ 2026 ГОДА (июль – декабрь, 6 месяцев × 10 млн = 60 млн)
A25: Сценарий | B25: Вложено (сум) | C25: Доход / Экономия (сум) | D25: Доход % | E25: Итого на руки (сум)
A26: 🏦 ИИС Облигации + НДФЛ | B26: 60000000 | C26: =B5*B10/12*(6*7/2)+B11*6*B5 -> 11400000 | D26: =C26/B26 -> 0.19 | E26: =B26+C26 -> 71400000
A27: 💳 Кредит (доп. платёж к погашению) | B27: 60000000 | C27: =B7/12*B5*6*(6-1)/2 -> 4125000 | D27: =C27/B27 -> 0.06875 | E27: =B27+C27 -> 64125000
A28: 🏧 Вклад 23% (с капитализацией) | B28: 60000000 | C28: =B5*((1+B12/12)^6-1)/(B12/12)-6*B5 -> 2687059.6 | D28: =C28/B28 -> 0.044784326 | E28: =B28+C28 -> 62687060

Sheet 🏦 ИИС Облигации
A1: ИИС ОБЛИГАЦИИ — ПОМЕСЯЧНЫЙ РАСЧЁТ (12 месяцев)
A3: Ежемесячный взнос (сум) | B3: ='📊 Сводка'!B5 -> 10000000
A4: Эффективная ставка ИИС (годовых) | B4: ='📊 Сводка'!B10 -> 0.24
A5: Ставка НДФЛ (возврат) | B5: ='📊 Сводка'!B11 -> 0.12
A6: Ежемесячная ставка ИИС | B6: =B5/12 -> 0.01
A7: Итого месяцев | B7: ='📊 Сводка'!B14 -> 12
A9: Месяц | B9: Ежемес. взнос (сум) | C9: Накопл. вложения (сум) | D9: Купонный доход (сум) | E9: Накопл. доход по купону | F9: НДФЛ (возврат) | G9: Итого доход нараст.
A10: Январь | B10: ='📊 Сводка'!B5 -> 10000000 | C10: =SUM(B10) -> 10000000 | D10: =C10*$B$6 -> 100000 | E10: =SUM(D10) -> 100000 | F10: ='📊 Сводка'!B11*'📊 Сводка'!B5 -> 1200000 | G10: =E10+SUM(F10) -> 1300000
A11: Февраль | B11: ='📊 Сводка'!B5 -> 10000000 | C11: =SUM(B10:B11) -> 20000000 | D11: =C11*$B$6 -> 200000 | E11: =SUM(D10:D11) -> 300000 | F11: ='📊 Сводка'!B11*'📊 Сводка'!B5 -> 1200000 | G11: =E11+SUM(F10:F11) -> 2700000
A12: Март | B12: ='📊 Сводка'!B5 -> 10000000 | C12: =SUM(B10:B12) -> 30000000 | D12: =C12*$B$6 -> 300000 | E12: =SUM(D10:D12) -> 600000 | F12: ='📊 Сводка'!B11*'📊 Сводка'!B5 -> 1200000 | G12: =E12+SUM(F10:F12) -> 4200000
A13: Апрель | B13: ='📊 Сводка'!B5 -> 10000000 | C13: =SUM(B10:B13) -> 40000000 | D13: =C13*$B$6 -> 400000 | E13: =SUM(D10:D13) -> 1000000 | F13: ='📊 Сводка'!B11*'📊 Сводка'!B5 -> 1200000 | G13: =E13+SUM(F10:F13) -> 5800000
A14: Май | B14: ='📊 Сводка'!B5 -> 10000000 | C14: =SUM(B10:B14) -> 50000000 | D14: =C14*$B$6 -> 500000 | E14: =SUM(D10:D14) -> 1500000 | F14: ='📊 Сводка'!B11*'📊 Сводка'!B5 -> 1200000 | G14: =E14+SUM(F10:F14) -> 7500000
A15: Июнь | B15: ='📊 Сводка'!B5 -> 10000000 | C15: =SUM(B10:B15) -> 60000000 | D15: =C15*$B$6 -> 600000 | E15: =SUM(D10:D15) -> 2100000 | F15: ='📊 Сводка'!B11*'📊 Сводка'!B5 -> 1200000 | G15: =E15+SUM(F10:F15) -> 9300000
A16: Июль | B16: ='📊 Сводка'!B5 -> 10000000 | C16: =SUM(B10:B16) -> 70000000 | D16: =C16*$B$6 -> 700000 | E16: =SUM(D10:D16) -> 2800000 | F16: ='📊 Сводка'!B11*'📊 Сводка'!B5 -> 1200000 | G16: =E16+SUM(F10:F16) -> 11200000
A17: Август | B17: ='📊 Сводка'!B5 -> 10000000 | C17: =SUM(B10:B17) -> 80000000 | D17: =C17*$B$6 -> 800000 | E17: =SUM(D10:D17) -> 3600000 | F17: ='📊 Сводка'!B11*'📊 Сводка'!B5 -> 1200000 | G17: =E17+SUM(F10:F17) -> 13200000
A18: Сентябрь | B18: ='📊 Сводка'!B5 -> 10000000 | C18: =SUM(B10:B18) -> 90000000 | D18: =C18*$B$6 -> 900000 | E18: =SUM(D10:D18) -> 4500000 | F18: ='📊 Сводка'!B11*'📊 Сводка'!B5 -> 1200000 | G18: =E18+SUM(F10:F18) -> 15300000
A19: Октябрь | B19: ='📊 Сводка'!B5 -> 10000000 | C19: =SUM(B10:B19) -> 100000000 | D19: =C19*$B$6 -> 1000000 | E19: =SUM(D10:D19) -> 5500000 | F19: ='📊 Сводка'!B11*'📊 Сводка'!B5 -> 1200000 | G19: =E19+SUM(F10:F19) -> 17500000
A20: Ноябрь | B20: ='📊 Сводка'!B5 -> 10000000 | C20: =SUM(B10:B20) -> 110000000 | D20: =C20*$B$6 -> 1100000 | E20: =SUM(D10:D20) -> 6600000 | F20: ='📊 Сводка'!B11*'📊 Сводка'!B5 -> 1200000 | G20: =E20+SUM(F10:F20) -> 19800000
A21: Декабрь | B21: ='📊 Сводка'!B5 -> 10000000 | C21: =SUM(B10:B21) -> 120000000 | D21: =C21*$B$6 -> 1200000 | E21: =SUM(D10:D21) -> 7800000 | F21: ='📊 Сводка'!B11*'📊 Сводка'!B5 -> 1200000 | G21: =E21+SUM(F10:F21) -> 22200000
A22: ИТОГО ЗА ГОД | B22: =SUM(B10:B21) -> 120000000 | C22: =C21 -> 120000000 | D22: =SUM(D10:D21) -> 7800000 | E22: =E21 -> 7800000 | F22: =SUM(F10:F21) -> 14400000 | G22: =G21 -> 22200000
A24: 📌 Итоговая доходность = Купонный доход + Возврат НДФЛ
A25: Общий купонный доход | B25: =E21 -> 7800000
A26: Возврат НДФЛ (12% от 120 млн) | B26: =SUM(F10:F21) -> 14400000
A27: ИТОГО ДОХОД | B27: =E21+SUM(F10:F21) -> 22200000
A28: Вложено всего | B28: =SUM(B10:B21) -> 120000000
A29: Доходность на вложенный капитал | B29: =(E21+SUM(F10:F21))/SUM(B10:B21) -> 0.185
A30: Эффективная годовая ставка (купон + НДФЛ) | B30: ='📊 Сводка'!B10+'📊 Сводка'!B11 -> 0.36

Sheet 💳 Кредит
A1: ПОГАШЕНИЕ КРЕДИТА — ПОМЕСЯЧНЫЙ РАСЧЁТ
A3: Начальный остаток кредита | B3: ='📊 Сводка'!B6 -> 170000000
A4: Годовая ставка кредита | B4: ='📊 Сводка'!B7 -> 0.33
A5: Ежемесячная ставка | B5: =B4/12 -> 0.0275
A6: Ежемесячный доп. платёж | B6: ='📊 Сводка'!B5 -> 10000000
A8: Месяц | B8: Остаток на начало (сум) | C8: Начисленные проценты (сум) | D8: Доп. платёж в основной долг (сум) | E8: Остаток на конец (сум) | F8: Проценты без доп. платежа | G8: Экономия процентов (сум)
A9: Январь | B9: =$B$3 -> 170000000 | C9: =B9*$B$5 -> 4675000 | D9: =$B$6 -> 10000000 | E9: =B9-D9 -> 160000000 | F9: =$B$3*$B$5 -> 4675000 | G9: =F9-C9 -> 0
A10: Февраль | B10: =E9 -> 160000000 | C10: =B10*$B$5 -> 4400000 | D10: =$B$6 -> 10000000 | E10: =B10-D10 -> 150000000 | F10: =$B$3*$B$5 -> 4675000 | G10: =F10-C10 -> 275000
A11: Март | B11: =E10 -> 150000000 | C11: =B11*$B$5 -> 4125000 | D11: =$B$6 -> 10000000 | E11: =B11-D11 -> 140000000 | F11: =$B$3*$B$5 -> 4675000 | G11: =F11-C11 -> 550000
A12: Апрель | B12: =E11 -> 140000000 | C12: =B12*$B$5 -> 3850000 | D12: =$B$6 -> 10000000 | E12: =B12-D12 -> 130000000 | F12: =$B$3*$B$5 -> 4675000 | G12: =F12-C12 -> 825000
A13: Май | B13: =E12 -> 130000000 | C13: =B13*$B$5 -> 3575000 | D13: =$B$6 -> 10000000 | E13: =B13-D13 -> 120000000 | F13: =$B$3*$B$5 -> 4675000 | G13: =F13-C13 -> 1100000
A14: Июнь | B14: =E13 -> 120000000 | C14: =B14*$B$5 -> 3300000 | D14: =$B$6 -> 10000000 | E14: =B14-D14 -> 110000000 | F14: =$B$3*$B$5 -> 4675000 | G14: =F14-C14 -> 1375000
A15: Июль | B15: =E14 -> 110000000 | C15: =B15*$B$5 -> 3025000 | D15: =$B$6 -> 10000000 | E15: =B15-D15 -> 100000000 | F15: =$B$3*$B$5 -> 4675000 | G15: =F15-C15 -> 1650000
A16: Август | B16: =E15 -> 100000000 | C16: =B16*$B$5 -> 2750000 | D16: =$B$6 -> 10000000 | E16: =B16-D16 -> 90000000 | F16: =$B$3*$B$5 -> 4675000 | G16: =F16-C16 -> 1925000
A17: Сентябрь | B17: =E16 -> 90000000 | C17: =B17*$B$5 -> 2475000 | D17: =$B$6 -> 10000000 | E17: =B17-D17 -> 80000000 | F17: =$B$3*$B$5 -> 4675000 | G17: =F17-C17 -> 2200000
A18: Октябрь | B18: =E17 -> 80000000 | C18: =B18*$B$5 -> 2200000 | D18: =$B$6 -> 10000000 | E18: =B18-D18 -> 70000000 | F18: =$B$3*$B$5 -> 4675000 | G18: =F18-C18 -> 2475000
A19: Ноябрь | B19: =E18 -> 70000000 | C19: =B19*$B$5 -> 1925000 | D19: =$B$6 -> 10000000 | E19: =B19-D19 -> 60000000 | F19: =$B$3*$B$5 -> 4675000 | G19: =F19-C19 -> 2750000
A20: Декабрь | B20: =E19 -> 60000000 | C20: =B20*$B$5 -> 1650000 | D20: =$B$6 -> 10000000 | E20: =B20-D20 -> 50000000 | F20: =$B$3*$B$5 -> 4675000 | G20: =F20-C20 -> 3025000
A21: ИТОГО ЗА ГОД | C21: =SUM(C9:C20) -> 37950000 | D21: =SUM(D9:D20) -> 120000000 | E21: =E20 -> 50000000 | F21: =SUM(F9:F20) -> 56100000 | G21: =SUM(G9:G20) -> 18150000
A23: 📌 Суммарная экономия = разница между процентами без доп. платежей и фактически уплаченными
A24: Начальный долг | B24: =$B$3 -> 170000000
A25: Остаток долга на конец года | B25: =E20 -> 50000000
A26: Погашено основного долга | B26: =$B$3-E20 -> 120000000
A27: Проценты уплачены (факт) | B27: =SUM(C9:C20) -> 37950000
A28: Проценты без доп. платежей | B28: =SUM(F9:F20) -> 56100000
A29: ЭКОНОМИЯ НА ПРОЦЕНТАХ | B29: =SUM(G9:G20) -> 18150000
A30: Доходность доп. платежей (%) | B30: =SUM(G9:G20)/SUM(D9:D20) -> 0.15125

Sheet 🏧 Вклад
A1: ВКЛАД С КАПИТАЛИЗАЦИЕЙ — ПОМЕСЯЧНЫЙ РАСЧЁТ
A3: Ежемесячный взнос | B3: ='📊 Сводка'!B5 -> 10000000
A4: Номинальная ставка (годовых) | B4: ='📊 Сводка'!B12 -> 0.21
A5: Эффективная ставка (годовых) | B5: ='📊 Сводка'!B13 -> 0.23
A6: Ежемесячная ставка | B6: =B4/12 -> 0.0175
A8: Месяц | B8: Взнос (сум) | C8: Нарастающий вклад (сум) | D8: Проценты за месяц (сум) | E8: Итого с процентами (сум) | F8: Итого процентов (сум)
A9: Январь | B9: ='📊 Сводка'!B5 -> 10000000 | C9: =SUM(B9) -> 10000000 | D9: =B9*$B$6 -> 175000 | E9: =B9+D9 -> 10175000 | F9: =SUM(D9) -> 175000
A10: Февраль | B10: ='📊 Сводка'!B5 -> 10000000 | C10: =SUM(B9:B10) -> 20000000 | D10: =E9*$B$6 -> 178062.5 | E10: =E9+B10+D10 -> 20353062 | F10: =SUM(D9:D10) -> 353062.5
A11: Март | B11: ='📊 Сводка'!B5 -> 10000000 | C11: =SUM(B9:B11) -> 30000000 | D11: =E10*$B$6 -> 356178.59 | E11: =E10+B11+D11 -> 30709241 | F11: =SUM(D9:D11) -> 709241.09
A12: Апрель | B12: ='📊 Сводка'!B5 -> 10000000 | C12: =SUM(B9:B12) -> 40000000 | D12: =E11*$B$6 -> 537411.72 | E12: =E11+B12+D12 -> 41246653 | F12: =SUM(D9:D12) -> 1246652.8
A13: Май | B13: ='📊 Сводка'!B5 -> 10000000 | C13: =SUM(B9:B13) -> 50000000 | D13: =E12*$B$6 -> 721816.42 | E13: =E12+B13+D13 -> 51968469 | F13: =SUM(D9:D13) -> 1968469.2
A14: Июнь | B14: ='📊 Сводка'!B5 -> 10000000 | C14: =SUM(B9:B14) -> 60000000 | D14: =E13*$B$6 -> 909448.21 | E14: =E13+B14+D14 -> 62877917 | F14: =SUM(D9:D14) -> 2877917.4
A15: Июль | B15: ='📊 Сводка'!B5 -> 10000000 | C15: =SUM(B9:B15) -> 70000000 | D15: =E14*$B$6 -> 1100363.6 | E15: =E14+B15+D15 -> 73978281 | F15: =SUM(D9:D15) -> 3978281
A16: Август | B16: ='📊 Сводка'!B5 -> 10000000 | C16: =SUM(B9:B16) -> 80000000 | D16: =E15*$B$6 -> 1294619.9 | E16: =E15+B16+D16 -> 85272901 | F16: =SUM(D9:D16) -> 5272900.9
A17: Сентябрь | B17: ='📊 Сводка'!B5 -> 10000000 | C17: =SUM(B9:B17) -> 90000000 | D17: =E16*$B$6 -> 1492275.8 | E17: =E16+B17+D17 -> 96765177 | F17: =SUM(D9:D17) -> 6765176.7
A18: Октябрь | B18: ='📊 Сводка'!B5 -> 10000000 | C18: =SUM(B9:B18) -> 100000000 | D18: =E17*$B$6 -> 1693390.6 | E18: =E17+B18+D18 -> 1.0845857e+08 | F18: =SUM(D9:D18) -> 8458567.3
A19: Ноябрь | B19: ='📊 Сводка'!B5 -> 10000000 | C19: =SUM(B9:B19) -> 110000000 | D19: =E18*$B$6 -> 1898024.9 | E19: =E18+B19+D19 -> 1.2035659e+08 | F19: =SUM(D9:D19) -> 10356592
A20: Декабрь | B20: ='📊 Сводка'!B5 -> 10000000 | C20: =SUM(B9:B20) -> 120000000 | D20: =E19*$B$6 -> 2106240.4 | E20: =E19+B20+D20 -> 1.3246283e+08 | F20: =SUM(D9:D20) -> 12462833
A21: ИТОГО ЗА ГОД | B21: =SUM(B9:B20) -> 120000000 | D21: =SUM(D9:D20) -> 12462833 | E21: =E20 -> 1.3246283e+08 | F21: =SUM(F9:F20) -> 54624694
A23: 📌 Итоги вклада
A24: Итоговая сумма вклада (с процентами) | B24: =E20 -> 1.3246283e+08
A25: Вложено итого | B25: =SUM(B9:B20) -> 120000000
A26: Доход (проценты) | B26: =E20-SUM(B9:B20) -> 12462833
A27: Доходность на вложенный капитал | B27: =(E20-SUM(B9:B20))/SUM(B9:B20) -> 0.10385694
A28: Эффективная годовая ставка | B28: ='📊 Сводка'!B13 -> 0.23

Sheet 🎯 Оптимальная стратегия
A1: ОПТИМАЛЬНАЯ СТРАТЕГИЯ — РЕКОМЕНДАЦИЯ
A3: 🏆 РАНЖИРОВАНИЕ ПО ЭФФЕКТИВНОЙ ДОХОДНОСТИ
A4: Инструмент | B4: Ставка купона/ основная ставка | C4: Эффект доп. фактора | D4: Итоговая эффект. ставка | E4: Риск | F4: Рекомендация
A5: 🥇 #1 — ИИС Облигации | B5: ='📊 Сводка'!B10 -> 0.24 | C5: +'📊 Сводка'!B11 НДФЛ | D5: ='📊 Сводка'!B10+'📊 Сводка'!B11 -> 0.36 | E5: Средний | F5: ✅ МАКСИМАЛЬНЫЙ ДОХОД → весь излишек сюда
A6: 🥈 #2 — Погашение кредита | B6: ='📊 Сводка'!B7 -> 0.33 | C6: Гарантия 33% | D6: ='📊 Сводка'!B7 -> 0.33 | E6: Нулевой | F6: ✅ Если нет лимита ИИС или хочешь снизить долг
A7: 🥉 #3 — Вклад | B7: ='📊 Сводка'!B13 -> 0.23 | C7: Капитализация учтена | D7: ='📊 Сводка'!B13 -> 0.23 | E7: Нулевой | F7: ✅ Только для ликвидного резерва (≤ 1-2 мес.)
A9: 💰 ЕЖЕМЕСЯЧНОЕ РАСПРЕДЕЛЕНИЕ 10 МЛН СУМ (ОПТИМАЛЬНАЯ СТРАТЕГИЯ)
A10: ШАГИ: 1️⃣ Весь излишек (10 000 000 сум) → ИИС Облигации (эффект. ставка 36%) → Купон 24% + Возврат НДФЛ 12% = ВЫГОДНЕЕ кредита на 3 п.п. 2️⃣ Если есть лимит на ИИС или хочешь активно снижать долг: → После ИИС остаток → досрочное погашение кредита (33% гарантия) 3️⃣ Вклад — только для аварийного резерва (1-2 месячных расхода) → НЕ основной инструмент, пока есть кредит под 33%
A15: 📊 ИТОГ ЧЕРЕЗ 12 МЕСЯЦЕВ (при инвестировании в ИИС)
A16: Вложено в ИИС за год | B16: ='📊 Сводка'!B14*'📊 Сводка'!B5 -> 120000000
A17: Купонный доход за год | B17: ='🏦 ИИС Облигации'!E21 -> 7800000
A18: Возврат НДФЛ за год | B18: =SUM('🏦 ИИС Облигации'!F10:F21) -> 14400000
A19: ИТОГО ДОХОД по ИИС | B19: ='🏦 ИИС Облигации'!G21 -> 22200000
A20: Остаток кредита (без доп. платежей) | B20: ='📊 Сводка'!B6 -> 170000000
A21: Выгода ИИС vs. Вклад за год | B21: ='🏦 ИИС Облигации'!G21-'🏧 Вклад'!F21 -> -32424694
A22: Выгода ИИС vs. Кредит за год | B22: ='🏦 ИИС Облигации'!G21-'💳 Кредит'!G21 -> 4050000
